README.md
setup.py
gerampai.egg-info/PKG-INFO
gerampai.egg-info/SOURCES.txt
gerampai.egg-info/dependency_links.txt
gerampai.egg-info/entry_points.txt
gerampai.egg-info/requires.txt
gerampai.egg-info/top_level.txt
gerampai.egg-info/zip-safe
src/__init__.py
src/gerampai.py