Metadata-Version: 2.1
Name: gerampai
Version: 0.1.2
Summary: Instagram extractor
Home-page: https://gitlab.com/wakataw/gerampai
Author: Agung Pratama
Author-email: agungpratama1001@gmail.com
License: MIT
Project-URL: Bug Reports, https://gitlab.com/wakataw/gerampai/issues
Project-URL: Source, https://gitlab.com/wakataw/gerampai
Keywords: instagram,scraper,data,extractor
Platform: UNKNOWN
Classifier: Development Status :: 4 - Beta
Classifier: Intended Audience :: Developers
Classifier: Topic :: Internet :: WWW/HTTP :: Dynamic Content :: CGI Tools/Libraries
Classifier: Topic :: Software Development :: Libraries :: Python Modules
Classifier: Topic :: Utilities
Classifier: Natural Language :: English
Classifier: Natural Language :: Indonesian
Classifier: Operating System :: OS Independent
Classifier: Programming Language :: Python :: 3.5
Classifier: License :: OSI Approved :: MIT License
Requires-Python: >=3.5
